[{
  "_id": {
    "$oid": "66f688d971216ec3770b9162"
  },
  "name": null,
  "Email": null,
  "Number": null,
  "Message": null
},
{
  "_id": {
    "$oid": "66f688ed71216ec3770b9163"
  },
  "name": "vbv",
  "Email": "marie@test.com",
  "Number": "12345678",
  "Message": "cghbjk,"
},
{
  "_id": {
    "$oid": "66f6890c71216ec3770b9164"
  },
  "name": "vbv",
  "Email": "marie@test.com",
  "Number": "12345678",
  "Message": "cghbjk,"
},
{
  "_id": {
    "$oid": "66f68ac371216ec3770b916e"
  },
  "name": "babi magi",
  "Email": "babiyolamaginot@gmail.com",
  "Number": "12345678",
  "Message": "good website"
},
{
  "_id": {
    "$oid": "66f68be771216ec3770b916f"
  },
  "name": "babi magi",
  "Email": "babiyolamaginot@gmail.com",
  "Number": "12345678",
  "Message": "good website"
},
{
  "_id": {
    "$oid": "66f68c1771216ec3770b9170"
  },
  "name": "Babiyola CH",
  "Email": "m@gmail.com",
  "Number": "1234568",
  "Message": "books a available"
},
{
  "_id": {
    "$oid": "66f6a1c471216ec3770b9171"
  },
  "name": "jnnk mah",
  "Email": "test@gmail.com",
  "Number": "354785224",
  "Message": "hello user"
}]